imsis/__init__.py
imsis/analyze.py
imsis/dialogs.py
imsis/image.py
imsis/imagestack.py
imsis/logging.py
imsis/misc.py
imsis/view.py
IMSIS-1.1.9.dist-info/LICENSE
IMSIS-1.1.9.dist-info/LICENSE.txt
IMSIS-1.1.9.dist-info/METADATA
IMSIS-1.1.9.dist-info/WHEEL
IMSIS-1.1.9.dist-info/top_level.txt
IMSIS-1.1.9.dist-info/RECORD
