Metadata-Version: 2.1
Name: IMSIS
Version: 1.1.9
Summary: IMSIS
Home-page: https://github.com/rengezri
Download-URL: https://github.com/rengezri/imsis/archive/refs/tags/v1.1.9.tar.gz
Author: rengezri
Author-email: rengezri <author@example.com>
License: MIT
Project-URL: Homepage, https://github.com/rengezri/imsis
Project-URL: Bug Tracker, https://github.com/rengezri/imsis/issues
Keywords: image analysis,dialogs,batch processing
Classifier: Programming Language :: Python :: 3
Classifier: License :: OSI Approved :: MIT License
Classifier: Operating System :: OS Independent
Requires-Python: >=3.6
License-File: LICENSE
License-File: LICENSE.txt
Requires-Dist: markdown
